lit_data/__init__.py
lit_data/main.py
lit_data-0.1.0.dist-info/LICENSE
lit_data-0.1.0.dist-info/WHEEL
lit_data-0.1.0.dist-info/METADATA
lit_data-0.1.0.dist-info/RECORD
